Workbook

Sheet Medicine_Sales_MessyData_2025
A1: Sale_ID | B1: Sale_Date | C1: Region | D1: State | E1: City | F1: Gender | G1: Age_Group | H1: Season | I1: Disease | J1: Medicine_Name | K1: Quantity_Sold | L1: Unit_Price | M1: Discount_% | N1: Total_Amount | O1: Sales_Channel | P1: Payment_Mode | Q1: Doctor_Prescribed | R1: Return_Flag | S1: Customer_Rating | T1: Remarks
A2: 1 | B2: 45985 | C2: North | D2: CA | E2: City_48 | F2: Other | G2: 19-35 | H2: Summer | I2: Diabetes | J2: MedA | K2: 44 | L2: 75.36 | O2: Online | P2: cash | Q2: Yes | R2: Y | S2: 1 | T2: Repeat customer
A3: 2 | B3: 45777 | C3: Central | D3: IL | E3: City_2 | F3: F | G3: 19-35 | H3: winter | I3: Cold | J3: MedB | K3: 29 | L3: 60.98 | M3: 0 | O3: Retail | P3: cash | Q3: yes | R3: N | S3: 2 | T3: Repeat customer
A4: 3 | B4: 45830 | C4: North | D4: CA | E4: City_25 | F4: Male | G4: 36-60 | H4: Monsoon | I4: Asthma | J4: MedC | K4: 3 | L4: 74.32 | O4: Online | P4: cash | Q4: Yes | S4: 3 | T4: First visit
A5: 4 | B5: 45953 | C5: South | D5: ca | E5: City_5 | F5: Male | H5: Summer | I5: Hypertension | J5: MedA | K5: 15 | L5: 87.32 | M5: 15 | O5: Hospital | P5: cash | Q5: yes | R5: Y | S5: 3 | T5: First visit
A6: 5 | B6: 45765 | C6: north | D6: NY | E6: City_45 | H6: Winter | I6: Asthma | J6: MedB | K6: 35 | L6: 74.27 | M6: 5 | O6: online | P6: cash | Q6: yes | T6: Repeat customer
A7: 6 | B7: 46008 | C7: East | D7: Tx | E7: City_50 | F7: Male | G7: 19-35 | H7: Winter | I7: Hypertension | J7: MedD | K7: 18 | L7: 11.29 | O7: Hospital | P7: Card | Q7: no | R7: N
A8: 7 | B8: 45731 | C8: East | D8: TX | E8: City_16 | G8: 19 -35 | H8: winter | I8: Hypertension | J8: MedD | K8: 38 | L8: 42.94 | M8: 5 | O8: Retail | P8: cash | Q8: Yes | R8: Y | S8: 1 | T8: Repeat customer
A9: 8 | B9: 45979 | C9: South | D9: Tx | E9: City_44 | F9: M | G9: 19 -35 | H9: Winter | I9: Cold | J9: MedD | K9: 39 | L9: 99.63 | O9: Hospital | P9: Cash | Q9: Yes | S9: 5 | T9: First visit
A10: 9 | B10: 45986 | C10: East | D10: CA | E10: City_19 | F10: M | G10: 19-35 | H10: Spring | I10: Flu | J10: MedC | K10: 33 | L10: 77.39 | O10: Online | P10: UPI | Q10: No | R10: Y | S10: 3 | T10: Repeat customer
A11: 10 | B11: 45934 | C11: SOUTH | D11: IL | E11: City_1 | F11: F | G11: 36-60 | H11: Spring | I11: Flu | J11: MedA | K11: 24 | L11: 88.48 | M11: 10 | O11: Retail | P11: Cash | Q11: No | S11: 1
A12: 11 | B12: 45906 | C12: SOUTH | D12: CA | E12: City_49 | F12: F | G12: 19-35 | H12: Summer | I12: Cold | J12: MedB | K12: 17 | L12: 55.13 | O12: online | P12: Card | Q12: No | S12: 3
A13: 12 | B13: 46001 | C13: north | D13: NY | E13: City_29 | F13: F | G13: 60+ | H13: Winter | I13: Diabetes | J13: MedB | K13: 5 | L13: 37.12 | O13: Retail | P13: Card | Q13: Yes | R13: Y
A14: 13 | B14: 45775 | C14: North | D14: CA | E14: City_22 | F14: Male | G14: 19 -35 | H14: Summer | I14: Hypertension | J14: MedD | K14: 14 | L14: 56.23 | O14: online | P14: Card | Q14: no | R14: N | S14: 2
A15: 14 | B15: 45707 | C15: north | D15: FL | E15: City_23 | F15: M | G15: 60+ | H15: Spring | I15: Flu | J15: MedA | K15: 4 | L15: 43.25 | M15: 10 | O15: Online | P15: Card | Q15: No | R15: Y | S15: 5
A16: 15 | B16: 45729 | C16: West | D16: TX | E16: City_18 | F16: M | G16: 19-35 | H16: Winter | I16: Cold | J16: MedA | K16: 4 | L16: 66.95 | O16: Online | P16: Cash | Q16: No | R16: Y | S16: 4
A17: 16 | B17: 45904 | C17: South | D17: Tx | E17: City_26 | F17: Male | G17: 19-35 | H17: Spring | I17: Flu | J17: MedD | K17: 17 | L17: 93.02 | M17: 15 | O17: Hospital | P17: cash | Q17: no | R17: Y | S17: 2 | T17: First visit
A18: 17 | B18: 45769 | C18: North | D18: IL | E18: City_48 | F18: F | G18: 0-18 | H18: Monsoon | I18: Flu | J18: MedA | K18: 38 | L18: 50.29 | O18: Retail | P18: Cash | Q18: Yes | R18: Y | S18: 1
A19: 18 | B19: 46003 | C19: SOUTH | D19: TX | E19: City_26 | F19: Male | G19: 19 -35 | H19: Summer | I19: Asthma | J19: MedA | K19: 40 | L19: 12.79 | O19: Hospital | P19: UPI | Q19: No | T19: First visit
A20: 19 | B20: 45780 | C20: East | D20: FL | E20: City_9 | H20: Monsoon | I20: Cold | J20: MedC | K20: 49 | L20: 93.89 | M20: 0 | O20: online | P20: Cash | Q20: Yes | S20: 2 | T20: First visit
A21: 20 | B21: 45725 | C21: East | D21: CA | E21: City_16 | F21: Other | G21: 36-60 | H21: Summer | I21: Cold | J21: MedC | K21: 40 | L21: 98.47 | O21: Online | P21: UPI | Q21: Yes | R21: Y | S21: 3
A22: 21 | B22: 45712 | C22: north | D22: IL | E22: City_10 | F22: Other | G22: 36-60 | H22: winter | I22: Diabetes | J22: MedC | K22: 14 | L22: 70.31 | M22: 10 | O22: online | P22: UPI | Q22: Yes | R22: Y
A23: 22 | B23: 45799 | C23: North | D23: CA | E23: City_22 | F23: Female | H23: Monsoon | I23: Diabetes | J23: MedD | K23: 36 | L23: 72.04 | O23: Online | P23: Cash | Q23: Yes | S23: 2
A24: 23 | B24: 45847 | C24: Central | D24: IL | E24: City_10 | F24: M | G24: 19-35 | H24: Winter | I24: Hypertension | J24: MedC | K24: 3 | L24: 90.4 | M24: 5 | O24: Retail | P24: Cash | Q24: yes | S24: 4 | T24: Repeat customer
A25: 24 | B25: 45779 | C25: SOUTH | D25: TX | E25: City_12 | F25: M | G25: 0-18 | H25: Summer | I25: Hypertension | J25: MedD | K25: 43 | L25: 87.09 | M25: 5 | O25: Hospital | P25: Card | Q25: Yes | R25: N | S25: 1
A26: 25 | B26: 45771 | C26: South | D26: Tx | E26: City_30 | F26: Other | G26: 36-60 | H26: Summer | I26: Diabetes | J26: MedA | K26: 43 | L26: 23.35 | M26: 10 | O26: Hospital | P26: Cash | Q26: yes | R26: N
A27: 26 | B27: 46005 | C27: SOUTH | D27: IL | E27: City_22 | F27: Male | G27: 0-18 | H27: Monsoon | I27: Diabetes | J27: MedC | K27: 3 | L27: 15.3 | M27: 15 | O27: Hospital | P27: UPI | Q27: no | S27: 5
A28: 27 | B28: 45855 | C28: Central | D28: TX | E28: City_17 | F28: Male | H28: Spring | I28: Flu | J28: MedB | K28: 24 | L28: 45.97 | M28: 10 | O28: Hospital | P28: Cash | Q28: yes | S28: 3
A29: 28 | B29: 45825 | C29: West | D29: ca | E29: City_19 | F29: F | G29: 19-35 | H29: Summer | I29: Cold | J29: MedD | K29: 44 | L29: 76.07 | M29: 5 | O29: Hospital | P29: cash | Q29: Yes | R29: N | S29: 3 | T29: Repeat customer
A30: 29 | B30: 45878 | C30: SOUTH | D30: IL | E30: City_39 | G30: 36-60 | H30: Spring | I30: Cold | J30: MedD | K30: 44 | L30: 25.3 | M30: 15 | O30: Retail | P30: Cash | Q30: yes | T30: First visit
A31: 30 | B31: 45705 | C31: SOUTH | D31: Tx | E31: City_16 | G31: 36-60 | H31: Summer | I31: Diabetes | J31: MedB | K31: 2 | L31: 9.39 | M31: 15 | O31: Online | P31: cash | Q31: no | S31: 5 | T31: Repeat customer
A32: 31 | B32: 46014 | C32: West | D32: FL | E32: City_26 | F32: Female | G32: 19-35 | H32: Winter | I32: Flu | J32: MedD | K32: 15 | L32: 21.71 | O32: online | P32: Cash | Q32: No | R32: Y | S32: 4 | T32: Repeat customer
A33: 32 | B33: 45895 | C33: north | D33: IL | E33: City_36 | F33: F | G33: 36-60 | H33: Spring | I33: Asthma | J33: MedD | K33: 36 | L33: 47.36 | M33: 5 | O33: online | P33: cash | Q33: yes | R33: Y | T33: First visit
A34: 33 | B34: 45924 | C34: West | D34: ca | E34: City_16 | F34: Other | G34: 60+ | H34: Winter | I34: Hypertension | J34: MedB | K34: 18 | L34: 36.91 | O34: Online | P34: Card | Q34: No | R34: Y | S34: 4 | T34: Repeat customer
A35: 34 | B35: 46019 | C35: South | D35: CA | E35: City_27 | F35: M | G35: 36-60 | H35: winter | I35: Cold | J35: MedD | K35: 4 | L35: 24.65 | M35: 15 | O35: online | P35: Cash | Q35: no | R35: N | S35: 1 | T35: First visit
A36: 35 | B36: 45810 | C36: SOUTH | D36: FL | E36: City_27 | F36: F | H36: winter | I36: Asthma | J36: MedB | K36: 32 | L36: 25.85 | M36: 15 | O36: online | P36: Cash | Q36: no | R36: N
A37: 36 | B37: 45742 | C37: SOUTH | D37: FL | E37: City_9 | F37: F | G37: 19 -35 | H37: Winter | I37: Cold | J37: MedA | K37: 6 | L37: 66.06 | M37: 5 | O37: online | P37: Card | Q37: Yes | R37: N | S37: 4 | T37: First visit
A38: 37 | B38: 45766 | C38: West | D38: NY | E38: City_22 | F38: M | G38: 36-60 | H38: Spring | I38: Hypertension | J38: MedA | K38: 31 | L38: 6.84 | O38: Online | P38: UPI | Q38: No | S38: 1
A39: 38 | B39: 45673 | C39: South | D39: TX | E39: City_2 | F39: F | G39: 19-35 | H39: Summer | I39: Diabetes | J39: MedD | K39: 43 | L39: 15.87 | M39: 5 | O39: online | P39: UPI | Q39: yes | R39: Y | S39: 5
A40: 39 | B40: 45741 | C40: East | D40: CA | E40: City_38 | F40: Male | G40: 36-60 | H40: winter | I40: Cold | J40: MedD | K40: 46 | L40: 23.84 | O40: Retail | P40: Cash | Q40: yes | S40: 5
A41: 40 | B41: 45947 | C41: SOUTH | D41: CA | E41: City_23 | F41: F | G41: 60+ | H41: Monsoon | I41: Flu | J41: MedC | K41: 1 | L41: 85.71 | M41: 15 | O41: Online | P41: cash | Q41: yes | S41: 4 | T41: Repeat customer
A42: 41 | B42: 45880 | C42: South | D42: ca | E42: City_34 | G42: 36-60 | H42: winter | I42: Asthma | J42: MedD | K42: 30 | L42: 46.38 | O42: Hospital | P42: UPI | Q42: No | R42: Y | S42: 3
A43: 42 | B43: 45782 | C43: SOUTH | D43: FL | E43: City_37 | F43: F | H43: Spring | I43: Hypertension | J43: MedA | K43: 32 | L43: 85.84 | M43: 5 | O43: online | P43: Card | Q43: yes | R43: N | S43: 3 | T43: First visit
A44: 43 | B44: 45963 | C44: north | D44: NY | E44: City_36 | F44: Male | G44: 19 -35 | H44: Summer | I44: Flu | J44: MedB | K44: 47 | L44: 43.61 | O44: Retail | P44: cash | Q44: no | R44: N | S44: 1
A45: 44 | B45: 45808 | C45: South | D45: FL | E45: City_45 | F45: Female | G45: 36-60 | H45: winter | I45: Hypertension | J45: MedD | K45: 36 | L45: 55.44 | M45: 15 | O45: Hospital | P45: UPI | Q45: no | R45: N | S45: 3 | T45: First visit
A46: 45 | B46: 45776 | C46: North | D46: ca | E46: City_13 | F46: Other | G46: 0-18 | H46: winter | I46: Diabetes | J46: MedB | K46: 14 | L46: 75.17 | M46: 10 | O46: Hospital | P46: Cash | Q46: No | R46: N | S46: 2 | T46: First visit
A47: 46 | B47: 45749 | C47: East | D47: CA | E47: City_46 | F47: F | G47: 19-35 | H47: Monsoon | I47: Flu | J47: MedA | K47: 36 | L47: 32.75 | M47: 5 | O47: online | P47: Cash | Q47: Yes | S47: 3
A48: 47 | B48: 45903 | C48: West | D48: NY | E48: City_12 | F48: Male | G48: 36-60 | H48: Spring | I48: Flu | J48: MedA | K48: 26 | L48: 51.72 | O48: Online | P48: Card | Q48: No | S48: 3
A49: 48 | B49: 45785 | C49: North | D49: IL | E49: City_49 | F49: M | G49: 19 -35 | H49: winter | I49: Asthma | J49: MedB | K49: 50 | L49: 54.64 | M49: 15 | O49: online | P49: UPI | Q49: no | R49: N | S49: 5
A50: 49 | B50: 45970 | C50: north | D50: CA | E50: City_49 | F50: Female | H50: Summer | I50: Hypertension | J50: MedA | K50: 11 | L50: 27.79 | O50: Online | P50: Card | Q50: Yes | R50: N | S50: 4
A51: 50 | B51: 45807 | C51: North | D51: TX | E51: City_19 | G51: 36-60 | H51: Spring | I51: Flu | J51: MedB | K51: 17 | L51: 79.84 | O51: Retail | P51: cash | Q51: Yes | S51: 2 | T51: Repeat customer
A52: 51 | B52: 45794 | C52: SOUTH | D52: TX | E52: City_5 | F52: Male | G52: 19-35 | H52: Monsoon | I52: Asthma | J52: MedC | K52: 29 | L52: 16.81 | M52: 10 | O52: online | P52: UPI | Q52: no | R52: N | S52: 1
A53: 52 | B53: 45879 | C53: north | D53: NY | E53: City_39 | F53: Other | G53: 0-18 | H53: Winter | I53: Diabetes | J53: MedA | K53: 49 | L53: 68.87 | M53: 10 | O53: Online | P53: Card | Q53: no
A54: 53 | B54: 45800 | C54: South | D54: IL | E54: City_28 | G54: 60+ | H54: Winter | I54: Cold | J54: MedC | K54: 27 | L54: 36.66 | M54: 0 | O54: Retail | P54: UPI | Q54: no | S54: 4 | T54: First visit
A55: 54 | B55: 45997 | C55: West | D55: Tx | E55: City_49 | F55: F | G55: 0-18 | H55: Spring | I55: Flu | J55: MedC | K55: 17 | L55: 35.71 | M55: 15 | O55: Online | P55: cash | Q55: no | R55: Y | S55: 2 | T55: First visit
A56: 55 | B56: 45976 | C56: SOUTH | D56: FL | E56: City_41 | F56: M | G56: 0-18 | H56: Summer | I56: Hypertension | J56: MedB | K56: 19 | L56: 46.62 | M56: 15 | O56: Online | P56: Cash | Q56: No | S56: 2 | T56: First visit
A57: 56 | B57: 45940 | C57: North | D57: IL | E57: City_27 | F57: Male | G57: 19-35 | H57: Winter | I57: Cold | J57: MedA | K57: 42 | L57: 84.05 | M57: 15 | O57: Hospital | P57: UPI | Q57: no | R57: N | S57: 4 | T57: Repeat customer
A58: 57 | B58: 45891 | C58: Central | D58: TX | E58: City_25 | F58: Female | G58: 19 -35 | H58: winter | I58: Diabetes | J58: MedA | K58: 18 | L58: 78.4 | M58: 15 | O58: Hospital | P58: UPI | Q58: Yes | R58: N | T58: First visit
A59: 58 | B59: 45958 | C59: Central | D59: ca | E59: City_32 | F59: Female | G59: 60+ | H59: winter | I59: Cold | J59: MedC | K59: 22 | L59: 57.43 | O59: online | P59: cash | Q59: yes | R59: Y | T59: Repeat customer
A60: 59 | B60: 45950 | C60: West | D60: TX | E60: City_50 | F60: M | G60: 0-18 | H60: Monsoon | I60: Cold | J60: MedD | K60: 25 | L60: 98.9 | M60: 5 | O60: online | P60: Cash | Q60: No | S60: 5 | T60: First visit
A61: 60 | B61: 45709 | C61: SOUTH | D61: Tx | E61: City_29 | F61: Male | G61: 19 -35 | H61: Spring | I61: Flu | J61: MedB | K61: 27 | L61: 87.74 | M61: 5 | O61: Online | P61: cash | Q61: yes | R61: N | S61: 5
A62: 61 | B62: 45990 | C62: North | D62: Tx | E62: City_22 | G62: 19 -35 | H62: Spring | I62: Hypertension | J62: MedD | K62: 35 | L62: 8.41 | M62: 0 | O62: Retail | P62: UPI | Q62: No | S62: 1
A63: 62 | B63: 45708 | C63: SOUTH | D63: ca | E63: City_46 | F63: Male | G63: 60+ | H63: Summer | I63: Hypertension | J63: MedA | K63: 3 | L63: 35.82 | M63: 0 | O63: Hospital | P63: UPI | Q63: yes | R63: N | S63: 2 | T63: Repeat customer
A64: 63 | B64: 45929 | C64: West | D64: IL | E64: City_44 | F64: Female | G64: 19-35 | H64: Summer | I64: Flu | J64: MedD | K64: 40 | L64: 69.9 | M64: 15 | O64: Retail | P64: Card | Q64: no | S64: 3
A65: 64 | B65: 45788 | C65: north | D65: CA | E65: City_30 | F65: Other | H65: winter | I65: Diabetes | J65: MedA | K65: 29 | L65: 94.8 | O65: Hospital | P65: cash | Q65: yes | R65: N | S65: 3 | T65: Repeat customer
A66: 65 | B66: 45854 | C66: SOUTH | D66: FL | E66: City_7 | F66: Female | G66: 60+ | H66: winter | I66: Hypertension | J66: MedC | K66: 45 | L66: 33.05 | M66: 15 | O66: Hospital | P66: Cash | Q66: Yes
A67: 66 | B67: 45804 | C67: SOUTH | D67: Tx | E67: City_15 | F67: F | G67: 36-60 | H67: Summer | I67: Diabetes | J67: MedC | K67: 44 | L67: 76.78 | M67: 5 | O67: Online | P67: Cash | Q67: yes | R67: N | S67: 1 | T67: First visit
A68: 67 | B68: 45725 | C68: North | D68: NY | E68: City_21 | G68: 60+ | H68: Summer | I68: Diabetes | J68: MedB | K68: 35 | L68: 88.26 | M68: 10 | O68: Hospital | P68: Card | Q68: yes | R68: N | S68: 3 | T68: First visit
A69: 68 | B69: 45716 | C69: West | D69: CA | E69: City_10 | F69: Female | H69: Spring | I69: Asthma | J69: MedC | K69: 6 | L69: 80.11 | M69: 0 | O69: Hospital | P69: Cash | Q69: no | R69: N | T69: First visit
A70: 69 | B70: 45957 | C70: West | D70: Tx | E70: City_41 | F70: Other | G70: 0-18 | H70: Summer | I70: Cold | J70: MedA | K70: 40 | L70: 89 | O70: Hospital | P70: Card | Q70: Yes | S70: 4 | T70: First visit
A71: 70 | B71: 45990 | C71: West | D71: CA | E71: City_9 | F71: Male | G71: 0-18 | H71: Monsoon | I71: Cold | J71: MedA | K71: 7 | L71: 27.31 | O71: Retail | P71: cash | Q71: no | R71: N
A72: 71 | B72: 45958 | C72: north | D72: ca | E72: City_10 | F72: M | H72: Winter | I72: Cold | J72: MedD | K72: 18 | L72: 8.11 | M72: 10 | O72: Retail | P72: cash | Q72: no | R72: Y | S72: 3
A73: 72 | B73: 46009 | C73: East | D73: IL | E73: City_42 | F73: Other | G73: 0-18 | H73: Spring | I73: Hypertension | J73: MedB | K73: 8 | L73: 95.16 | M73: 15 | O73: Online | P73: Card | Q73: Yes | R73: Y | S73: 3 | T73: Repeat customer
A74: 73 | B74: 45722 | C74: SOUTH | D74: IL | E74: City_14 | F74: Male | G74: 19 -35 | H74: Summer | I74: Asthma | J74: MedB | K74: 15 | L74: 36.21 | M74: 5 | O74: Online | P74: UPI | Q74: No | R74: Y | S74: 5 | T74: First visit
A75: 74 | B75: 45747 | C75: North | D75: ca | E75: City_2 | F75: Female | G75: 0-18 | H75: Monsoon | I75: Diabetes | J75: MedC | K75: 2 | L75: 21.55 | M75: 0 | O75: Retail | P75: cash | Q75: Yes | S75: 1
A76: 75 | B76: 45887 | C76: SOUTH | D76: NY | E76: City_33 | F76: F | G76: 0-18 | H76: Spring | I76: Asthma | J76: MedB | K76: 40 | L76: 9.12 | O76: Hospital | P76: cash | Q76: Yes | R76: Y | S76: 4
A77: 76 | B77: 45876 | C77: north | D77: CA | E77: City_32 | G77: 60+ | H77: Winter | I77: Flu | J77: MedC | K77: 39 | L77: 19.09 | M77: 5 | O77: Hospital | P77: UPI | Q77: no | S77: 5 | T77: First visit
A78: 77 | B78: 45890 | C78: Central | D78: IL | E78: City_28 | F78: Male | H78: Winter | I78: Asthma | J78: MedB | K78: 28 | L78: 47.9 | M78: 5 | O78: online | P78: UPI | Q78: no | R78: N | S78: 4
A79: 78 | B79: 45818 | C79: West | D79: NY | E79: City_43 | F79: Other | G79: 36-60 | H79: Summer | I79: Cold | J79: MedA | K79: 6 | L79: 84.02 | M79: 0 | O79: online | P79: Cash | Q79: yes | R79: Y | S79: 5
A80: 79 | B80: 45958 | C80: Central | D80: IL | E80: City_22 | G80: 0-18 | H80: Spring | I80: Hypertension | J80: MedD | K80: 47 | L80: 9.89 | M80: 10 | O80: Hospital | P80: UPI | Q80: Yes | S80: 5 | T80: Repeat customer
A81: 80 | B81: 45737 | C81: north | D81: FL | E81: City_15 | F81: Male | G81: 36-60 | H81: winter | I81: Hypertension | J81: MedA | K81: 49 | L81: 31.46 | M81: 5 | O81: online | P81: Cash | Q81: yes | R81: Y | S81: 2 | T81: First visit
A82: 81 | B82: 46017 | C82: SOUTH | D82: NY | E82: City_22 | F82: Other | G82: 0-18 | H82: Summer | I82: Diabetes | J82: MedD | K82: 5 | L82: 18.48 | M82: 0 | O82: Online | P82: Card | Q82: no | R82: N | S82: 4 | T82: First visit
A83: 82 | B83: 45738 | C83: East | D83: NY | E83: City_47 | F83: Other | G83: 19 -35 | H83: winter | I83: Flu | J83: MedA | K83: 10 | L83: 19.95 | O83: Online | P83: Cash | Q83: yes | R83: N
A84: 83 | B84: 45906 | C84: Central | D84: FL | E84: City_27 | F84: Other | G84: 19-35 | H84: winter | I84: Flu | J84: MedC | K84: 28 | L84: 15.53 | O84: online | P84: UPI | Q84: Yes | R84: Y | S84: 4
A85: 84 | B85: 45661 | C85: South | D85: NY | E85: City_14 | F85: Female | G85: 36-60 | H85: Monsoon | I85: Hypertension | J85: MedA | K85: 1 | L85: 52.25 | M85: 15 | O85: Retail | P85: Card | Q85: no | T85: Repeat customer
A86: 85 | B86: 45914 | C86: Central | D86: Tx | E86: City_43 | F86: Other | G86: 0-18 | H86: Spring | I86: Flu | J86: MedD | K86: 2 | L86: 48.68 | M86: 0 | O86: Hospital | P86: cash | Q86: no
A87: 86 | B87: 45806 | C87: North | D87: FL | E87: City_2 | F87: Other | G87: 19-35 | H87: winter | I87: Cold | J87: MedC | K87: 6 | L87: 46.49 | M87: 0 | O87: Retail | P87: cash | Q87: no | S87: 1
A88: 87 | B88: 45816 | C88: north | D88: NY | E88: City_15 | F88: Other | G88: 19-35 | H88: Winter | I88: Asthma | J88: MedA | K88: 34 | L88: 53.45 | M88: 10 | O88: Hospital | P88: Card | Q88: No | R88: Y | S88: 2 | T88: First visit
A89: 88 | B89: 45759 | C89: South | D89: IL | E89: City_10 | G89: 0-18 | H89: Summer | I89: Cold | J89: MedD | K89: 49 | L89: 58.55 | O89: online | P89: UPI | Q89: yes | R89: Y | S89: 4
A90: 89 | B90: 45898 | C90: West | D90: ca | E90: City_20 | F90: Other | G90: 19 -35 | H90: Winter | I90: Hypertension | J90: MedA | K90: 20 | L90: 48.87 | M90: 0 | O90: Online | P90: UPI | Q90: yes | R90: Y
A91: 90 | B91: 45972 | C91: Central | D91: IL | E91: City_25 | F91: M | G91: 19 -35 | H91: winter | I91: Flu | J91: MedD | K91: 37 | L91: 66.92 | M91: 10 | O91: online | P91: Card | Q91: Yes | R91: N | S91: 1 | T91: First visit
A92: 91 | B92: 45701 | C92: Central | D92: ca | E92: City_12 | F92: Male | G92: 19-35 | H92: Spring | I92: Cold | J92: MedB | K92: 24 | L92: 40.42 | M92: 10 | O92: online | P92: cash | Q92: yes | S92: 5
A93: 92 | B93: 45981 | C93: north | D93: NY | E93: City_5 | F93: Other | G93: 0-18 | H93: winter | I93: Cold | J93: MedC | K93: 17 | L93: 73.75 | O93: Retail | P93: UPI | Q93: Yes | T93: Repeat customer
A94: 93 | B94: 45837 | C94: East | D94: ca | E94: City_45 | G94: 60+ | H94: Summer | I94: Asthma | J94: MedA | K94: 20 | L94: 58.1 | M94: 10 | O94: Retail | P94: Cash | Q94: no | S94: 3
A95: 94 | B95: 45843 | C95: East | D95: TX | E95: City_14 | F95: Other | G95: 60+ | H95: Summer | I95: Diabetes | J95: MedB | K95: 10 | L95: 12.33 | M95: 0 | O95: Online | P95: UPI | Q95: No | S95: 4 | T95: Repeat customer
A96: 95 | B96: 45741 | C96: South | D96: Tx | E96: City_45 | F96: F | G96: 19-35 | H96: Spring | I96: Flu | J96: MedD | K96: 24 | L96: 69.25 | M96: 5 | O96: online | P96: UPI | Q96: no | R96: Y | S96: 5 | T96: Repeat customer
A97: 96 | B97: 45816 | C97: SOUTH | D97: Tx | E97: City_31 | F97: Female | G97: 36-60 | H97: winter | I97: Cold | J97: MedD | K97: 50 | L97: 31.77 | M97: 15 | O97: online | P97: Card | Q97: No | S97: 2 | T97: First visit
A98: 97 | B98: 45684 | C98: north | D98: FL | E98: City_24 | F98: F | G98: 0-18 | H98: winter | I98: Flu | J98: MedC | K98: 6 | L98: 77.5 | M98: 10 | O98: online | P98: Card | Q98: no | R98: Y | S98: 2
A99: 98 | B99: 45836 | C99: North | D99: FL | E99: City_4 | F99: M | G99: 19 -35 | H99: Monsoon | I99: Diabetes | J99: MedD | K99: 6 | L99: 40.62 | M99: 0 | O99: Hospital | P99: Cash | Q99: yes | R99: Y | S99: 2
A100: 99 | B100: 45804 | C100: SOUTH | D100: FL | E100: City_45 | F100: Female | H100: Spring | I100: Cold | J100: MedA | K100: 6 | L100: 6.81 | M100: 5 | O100: Retail | P100: cash | Q100: Yes | R100: N | S100: 2 | T100: First visit
...

Sheet Clean_DataSet
A1: Sale_ID | B1: Sale_Date | C1: Region | D1: State | E1: City | F1: Gender | G1: Age_Group | H1: Season | I1: Disease | J1: Medicine_Name | K1: Quantity_Sold | L1: Unit_Price | M1: Discount_% | N1: Total_Amount | O1: Sales_Channel | P1: Payment_Mode | Q1: Doctor_Prescribed | R1: Return_Flag | S1: Customer_Rating | T1: Remarks
A2: 1 | B2: 45985 | C2: North | D2: Ca | E2: City_48 | F2: Other | G2: 19-35 | H2: Summer | I2: Diabetes | J2: MedA | K2: 44 | L2: 75.36 | M2: 0 | N2: =PRODUCT(K2,L2) -> 3315.84 | O2: Online | P2: Cash | Q2: Yes | R2: Y | S2: 1 | T2: Repeat Customer
A3: 2 | B3: 45777 | C3: Central | D3: Il | E3: City_2 | F3: Female | G3: 19-35 | H3: Winter | I3: Cold | J3: MedB | K3: 29 | L3: 60.98 | M3: 0 | N3: =PRODUCT(K3,L3) -> 1768.42 | O3: Retail | P3: Cash | Q3: Yes | R3: N | S3: 2 | T3: Repeat Customer
A4: 3 | B4: 45830 | C4: North | D4: Ca | E4: City_25 | F4: Male | G4: 36-60 | H4: Monsoon | I4: Asthma | J4: MedC | K4: 3 | L4: 74.32 | M4: 0 | N4: =PRODUCT(K4,L4) -> 222.96 | O4: Online | P4: Cash | Q4: Yes | R4: N | S4: 3 | T4: First Visit
A5: 4 | B5: 45953 | C5: South | D5: Ca | E5: City_5 | F5: Male | G5: 26-40 | H5: Summer | I5: Hypertension | J5: MedA | K5: 15 | L5: 87.32 | M5: 15 | N5: =PRODUCT(K5,L5) -> 1309.8 | O5: Hospital | P5: Cash | Q5: Yes | R5: Y | S5: 3 | T5: First Visit
A6: 5 | B6: 45765 | C6: North | D6: Ny | E6: City_45 | F6: Unknown | G6: 26-40 | H6: Winter | I6: Asthma | J6: MedB | K6: 35 | L6: 74.27 | M6: 5 | N6: =PRODUCT(K6,L6) -> 2599.45 | O6: Online | P6: Cash | Q6: Yes | R6: N | S6: 3 | T6: Repeat Customer
A7: 6 | B7: 46008 | C7: East | D7: Tx | E7: City_50 | F7: Male | G7: 19-35 | H7: Winter | I7: Hypertension | J7: MedD | K7: 18 | L7: 11.29 | M7: 0 | N7: =PRODUCT(K7,L7) -> 203.22 | O7: Hospital | P7: Card | Q7: No | R7: N | S7: 3 | T7: No Feedback
A8: 7 | B8: 45731 | C8: East | D8: Tx | E8: City_16 | F8: Unknown | G8: 19 -35 | H8: Winter | I8: Hypertension | J8: MedD | K8: 38 | L8: 42.94 | M8: 5 | N8: =PRODUCT(K8,L8) -> 1631.72 | O8: Retail | P8: Cash | Q8: Yes | R8: Y | S8: 1 | T8: Repeat Customer
A9: 8 | B9: 45979 | C9: South | D9: Tx | E9: City_44 | F9: Male | G9: 19 -35 | H9: Winter | I9: Cold | J9: MedD | K9: 39 | L9: 99.63 | M9: 0 | N9: =PRODUCT(K9,L9) -> 3885.57 | O9: Hospital | P9: Cash | Q9: Yes | R9: N | S9: 5 | T9: First Visit
A10: 9 | B10: 45986 | C10: East | D10: Ca | E10: City_19 | F10: Male | G10: 19-35 | H10: Spring | I10: Flu | J10: MedC | K10: 33 | L10: 77.39 | M10: 0 | N10: =PRODUCT(K10,L10) -> 2553.87 | O10: Online | P10: Upi | Q10: No | R10: Y | S10: 3 | T10: Repeat Customer
A11: 10 | B11: 45934 | C11: South | D11: Il | E11: City_1 | F11: Female | G11: 36-60 | H11: Spring | I11: Flu | J11: MedA | K11: 24 | L11: 88.48 | M11: 10 | N11: =PRODUCT(K11,L11) -> 2123.52 | O11: Retail | P11: Cash | Q11: No | R11: N | S11: 1 | T11: No Feedback
A12: 11 | B12: 45906 | C12: South | D12: Ca | E12: City_49 | F12: Female | G12: 19-35 | H12: Summer | I12: Cold | J12: MedB | K12: 17 | L12: 55.13 | M12: 0 | N12: =PRODUCT(K12,L12) -> 937.21 | O12: Online | P12: Card | Q12: No | R12: N | S12: 3 | T12: No Feedback
A13: 12 | B13: 46001 | C13: North | D13: Ny | E13: City_29 | F13: Female | G13: 60+ | H13: Winter | I13: Diabetes | J13: MedB | K13: 5 | L13: 37.12 | M13: 0 | N13: =PRODUCT(K13,L13) -> 185.6 | O13: Retail | P13: Card | Q13: Yes | R13: Y | S13: 5 | T13: No Feedback
... A501: 500 | B501: 45768 | C501: South | D501: Tx | E501: City_48 | F501: Male | G501: 0-18 | H501: Winter | I501: Asthma | J501: MedC | K501: 5 | L501: 87.69 | M501: 15 | N501: =PRODUCT(K501,L501) -> 438.45 | O501: Online | P501: Upi | Q501: No | R501: N | S501: 4 | T501: No Feedback

Sheet Operation_Sheet
C2: How discounts affect total sales and revenue ?
C3: Avg_Discount | D3: =AVERAGE(Clean_DataSet!M2:M501) -> 5.79
C5: Which region and season generate the highest medicine sales?
C6: Region | D6: Season | E6: Sales
C7: North | D7: Winter | E7: =SUMIFS(Clean_DataSet!N2:N501,Clean_DataSet!C2:C501,C7,Clean_DataSet!H2:H501,D7) -> 86667.05
C9: Which age group and gender buy medicines?
C10: Gender | D10: Age_Group | E10: Result
C11: Unknown | D11: 36-60 | E11: =COUNTIFS(Clean_DataSet!F2:F501,C11,Clean_DataSet!G2:G501,D11) -> 23
C13: Selling medicines by disease and season
C14: Season | D14: Disease | E14: Result
C15: Summer | D15: Diabetes | E15: =SUMIFS(Clean_DataSet!K2:K501,Clean_DataSet!H2:H501,C15,Clean_DataSet!I2:I501,D15) -> 717
C17: Net revenue after discount ?
C18: Result
C19: {=SUMPRODUCT(Clean_DataSet!K2:K501*Clean_DataSet!L2:L501*(1-Clean_DataSet!M2:$M$501))} -> -3506892.5
C21: Which medicines generate the highest sales?
C22: Medicine_Name | D22: Result
C23: MedD | D23: {=SUMPRODUCT((Clean_DataSet!J2:J501=C23)*(Clean_DataSet!K2:K501*Clean_DataSet!L2:L501))} -> 209191.15

Sheet Pivot_Table_Sheet
A3: Season | B3: Sum of Total_Amount | D3: Region | E3: Sum of Quantity_Sold | G3: Age_Group | H3: Count of Disease | J3: Medicine_Name | K3: Sum of Quantity_Sold
A4: Monsoon | B4: 114307.76 | D4: Central | E4: 1757 | G4: 0-18 | H4: 85 | J4: MedA | K4: 3293
A5: Spring | B5: 140369.28 | D5: East | E5: 2124 | G5: 19 -35 | H5: 75 | J5: MedB | K5: 3269
A6: Summer | B6: 149362.33 | D6: North | E6: 3779 | G6: 19-35 | H6: 83 | J6: MedC | K6: 2847
A7: Winter | B7: 292031.77 | D7: South | E7: 3893 | G7: 26-40 | H7: 88 | J7: MedD | K7: 3975
D8: West | E8: 1831 | G8: 36-60 | H8: 102
G9: 60+ | H9: 67
A12: Disease | B12: Sum of Total_Amount | D12: Age_Group | E12: Sum of Total_Amount | G12: Discount_% | H12: Sum of Total_Amount | J12: Return_Flag | K12: Sum of Sale_ID | L12: Count of State
A13: Asthma | B13: 106770.91 | D13: 0-18 | E13: 123415.11 | G13: 0 | H13: 270422 | J13: N | K13: 85785 | L13: 346
A14: Cold | B14: 167091.61 | D14: 19 -35 | E14: 97467.45 | G14: 5 | H14: 157577.83 | J14: Y | K14: 39465 | L14: 154
A15: Diabetes | B15: 162238.89 | D15: 19-35 | E15: 112620.59 | G15: 10 | H15: 121199.03
A16: Flu | B16: 117715.44 | D16: 26-40 | E16: 123915.06 | G16: 15 | H16: 146872.28
A17: Hypertension | B17: 142254.29 | D17: 36-60 | E17: 152353.38
D18: 60+ | E18: 86299.55

Sheet Visualization_Sheet
